swfilter/__init__.py
swfilter/models.py
swfilter-0.1.dist-info/LICENSE
swfilter-0.1.dist-info/METADATA
swfilter-0.1.dist-info/WHEEL
swfilter-0.1.dist-info/top_level.txt
swfilter-0.1.dist-info/RECORD
